Metadata-Version: 1.0
Name: tmsg
Version: 0.1
Summary: A curses based client for Facebook Messenger
Home-page: https://github.com/andrewhalle/tmsg
Author: Andrew Halle
Author-email: ahalle@berkeley.edu
License: MIT
Platform: UNKNOWN
